mule/__init__.py
mule/logger.py
mule/ci/__init__.py
mule/ci/__main__.py
mule/ci/config.py
mule/ci/driver.py
mule/ci/parser.py
mule/ci/archetype/__init__.py
mule/ci/archetype/docker.py
mule/ci/archetype/node.py
mule/ci/archetype/util.py
mule/task/__init__.py
mule/task/__main__.py
mule/task/main.py
mule/task/mule.py
mule/task/parser.py
mule/task/algorand/__init__.py
mule/task/algorand/indexer.py
mule/task/algorand/node.py
mule/task/docker/__init__.py
mule/task/error/__init__.py
mule/task/error/messages.py
mule/task/release/__init__.py
mule/task/release/notes.py
mule/task/release/resources/notes.template.mustache
mule/task/s3/__init__.py
mule/task/s3/test/__init__.py
mule/task/s3/test/test_archive.py
mule/task/shell/__init__.py
mule/task/shell/kubernetes/__init__.py
mule/task/stash/__init__.py
mule/task/validator/__init__.py
mule/util/__init__.py
mule/util/algorand_util.py
mule/util/aws_util.py
mule/util/docker_util.py
mule/util/download_util.py
mule/util/file_util.py
mule/util/git_util.py
mule/util/github_util.py
mule/util/helm_util.py
mule/util/npm_util.py
mule/util/os_util.py
mule/util/s3_util.py
mule/util/semver_util.py
mule/util/shell_util.py
mule/util/time_util.py
mule/util/resources/charts/rest-api/Chart.yaml
mule/util/resources/charts/rest-api/values.yaml
mule/util/resources/charts/rest-api/templates/_helpers.tpl
mule/util/resources/charts/rest-api/templates/configmap.yaml
mule/util/resources/charts/rest-api/templates/deployment.yaml
mule/util/resources/charts/rest-api/templates/ingress.yaml
mule/util/resources/charts/rest-api/templates/service.yaml
mule/util/test/__init__.py
mule/util/test/test_s3_util.py
mule/util/yaml/__init__.py
mule/util/yaml/env_var_loader.py
mulecli-0.0.23.dist-info/LICENSE
mulecli-0.0.23.dist-info/METADATA
mulecli-0.0.23.dist-info/WHEEL
mulecli-0.0.23.dist-info/entry_points.txt
mulecli-0.0.23.dist-info/top_level.txt
mulecli-0.0.23.dist-info/RECORD
