Metadata-Version: 2.1
Name: mulecli
Version: 0.0.23
Summary: Script for executing automated tasks
Home-page: UNKNOWN
License: MIT
Platform: UNKNOWN
Classifier: License :: OSI Approved :: MIT License
Classifier: Programming Language :: Python
Classifier: Programming Language :: Python :: 3
Classifier: Programming Language :: Python :: 3.7
Requires-Python: >=3.5
Requires-Dist: boto3
Requires-Dist: botocore
Requires-Dist: gitpython
Requires-Dist: packaging
Requires-Dist: pygithub
Requires-Dist: pystache
Requires-Dist: pytest
Requires-Dist: pyyaml
Requires-Dist: wget
